sentient_typer/__init__.py
sentient_typer/terminal_typer.py
sentient_typer-1.1.0.dist-info/DESCRIPTION.rst
sentient_typer-1.1.0.dist-info/METADATA
sentient_typer-1.1.0.dist-info/RECORD
sentient_typer-1.1.0.dist-info/WHEEL
sentient_typer-1.1.0.dist-info/entry_points.txt
sentient_typer-1.1.0.dist-info/metadata.json
sentient_typer-1.1.0.dist-info/top_level.txt
