Metadata-Version: 2.0
Name: sentient-typer
Version: 1.1.0
Summary: Print text as if it is being typed by the computer
Home-page: https://github.com/Abhishek8394/sentient_typer
Author: Abhishek Patel
Author-email: apbytes@gmail.com
License: GPLv2
Keywords: typing terminal AI terminator
Platform: UNKNOWN
